operations/__init__.py
operations/add.py
ops/__init__.py
ops/add.py
ops-shuv/__init__.py
ops-shuv/add.py
ops_shuv/__init__.py
ops_shuv/ops.py
ops_shuv-0.4.dist-info/LICENSE
ops_shuv-0.4.dist-info/METADATA
ops_shuv-0.4.dist-info/WHEEL
ops_shuv-0.4.dist-info/top_level.txt
ops_shuv-0.4.dist-info/RECORD
