Metadata-Version: 2.1
Name: ops-shuv
Version: 0.4
Summary: this contains some kind operations in it.
Author: shuvam mandal
Author-email: shuvammandal121@gmail.com
License-File: LICENSE
